plus10.py
plus10-1.0.dist-info/METADATA
plus10-1.0.dist-info/WHEEL
plus10-1.0.dist-info/top_level.txt
plus10-1.0.dist-info/RECORD
