Metadata-Version: 2.1
Name: plus10
Version: 1.0
Summary: Why not to add 10?
Author: Who cares?
Author-email: name.surname@gmail.com
